io/__init__.py
io/file.py
dcode.py-0.0.2.dist-info/LICENSE
dcode.py-0.0.2.dist-info/METADATA
dcode.py-0.0.2.dist-info/WHEEL
dcode.py-0.0.2.dist-info/top_level.txt
dcode.py-0.0.2.dist-info/RECORD
