Metadata-Version: 2.1
Name: dcode.py
Version: 0.0.2
Summary: dcode - the Python package for everything
Author-email: Dylan Rogers <opendylan@proton.me>
Project-URL: Homepage, https://github.com/dylanopen/dcode.py
Project-URL: Bug Tracker, https://github.com/dylanopen/dcode.py/issues
Classifier: Programming Language :: Python :: 3
Classifier: License :: OSI Approved :: MIT License
Classifier: Operating System :: OS Independent
Requires-Python: >=2.0
License-File: LICENSE
